MANIFEST.in
README.md
setup.py
fileporter/__init__.py
fileporter/server.py
fileporter.egg-info/PKG-INFO
fileporter.egg-info/SOURCES.txt
fileporter.egg-info/dependency_links.txt
fileporter.egg-info/not-zip-safe
fileporter.egg-info/requires.txt
fileporter.egg-info/top_level.txt
fileporter/static/index.html
static/index.html