Metadata-Version: 1.0
Name: fileporter
Version: 1.8
Summary: support download/upload/browser,use tornado
Home-page: https://github.com/rfyiamcool/fileporter
Author: fengyun
Author-email: rfyiamcool@163.com
License: BSD
Keywords: better SimpleHTTPServer fengyun
Platform: UNKNOWN
Classifier: Development Status :: 4 - Beta
Classifier: Environment :: Console
Classifier: Intended Audience :: Developers
Classifier: Intended Audience :: System Administrators
Classifier: License :: OSI Approved :: BSD License
Classifier: Topic :: Utilities
